{
    "version": "2024-09-10-0532",
    "description": "Roguelike in a post-apocalyptic world (with sprite-based graphics, experimental build)",
    "homepage": "https://cataclysmdda.org",
    "license": "CC-BY-SA-3.0",
    "architecture": {
        "64bit": {
            "url": "https://github.com/CleverRaven/Cataclysm-DDA/releases/download/cdda-experimental-2024-09-10-0532/cdda-windows-tiles-sounds-x64-msvc-2024-09-10-0532.zip",
            "hash": "58f565f12abb2bd9d10859b6b8f7d5bf620ae7cbb70f8eae57dfc4ff82834c27"
        }
    },
    "shortcuts": [
        [
            "cataclysm-tiles.exe",
            "Cataclysm DDA\\Cataclysm DDA Tiles (Experimental)"
        ]
    ],
    "persist": [
        "config",
        "save",
        "sound",
        "templates"
    ],
    "checkver": {
        "url": "https://github.com/CleverRaven/Cataclysm-DDA/releases/",
        "re": "Cataclysm-DDA experimental build ([\\d.-]+)"
    },
    "autoupdate": {
        "architecture": {
            "64bit": {
                "url": "https://github.com/CleverRaven/Cataclysm-DDA/releases/download/cdda-experimental-$version/cdda-windows-tiles-sounds-x64-msvc-$version.zip"
            }
        }
    }
}
