{
    "version": "2024-10-02-0858",
    "description": "Roguelike in a post-apocalyptic world (with sprite-based graphics, experimental build)",
    "homepage": "https://cataclysmdda.org",
    "license": "CC-BY-SA-3.0",
    "architecture": {
        "64bit": {
            "url": "https://github.com/CleverRaven/Cataclysm-DDA/releases/download/cdda-experimental-2024-10-02-0858/cdda-windows-tiles-sounds-x64-msvc-2024-10-02-0858.zip",
            "hash": "64cbd74072ef902ea9a334a45d33b5878afb321e8a298df695346bc41f8f1401"
        }
    },
    "shortcuts": [
        [
            "cataclysm-tiles.exe",
            "Cataclysm DDA\\Cataclysm DDA Tiles (Experimental)"
        ]
    ],
    "persist": [
        "config",
        "save",
        "sound",
        "templates"
    ],
    "checkver": {
        "url": "https://github.com/CleverRaven/Cataclysm-DDA/releases/",
        "re": "Cataclysm-DDA experimental build ([\\d.-]+)"
    },
    "autoupdate": {
        "architecture": {
            "64bit": {
                "url": "https://github.com/CleverRaven/Cataclysm-DDA/releases/download/cdda-experimental-$version/cdda-windows-tiles-sounds-x64-msvc-$version.zip"
            }
        }
    }
}
