{
    "version": "2024-02-27-0320",
    "description": "Roguelike in a post-apocalyptic world (with sprite-based graphics, experimental build)",
    "homepage": "https://cataclysmdda.org",
    "license": "CC-BY-SA-3.0",
    "architecture": {
        "64bit": {
            "url": "https://github.com/CleverRaven/Cataclysm-DDA/releases/download/cdda-experimental-2024-02-27-0320/cdda-windows-tiles-sounds-x64-msvc-2024-02-27-0320.zip",
            "hash": "01ce168bb5f303a33043681f652b6701fb260869efe133f99a71e37fa122d92b"
        }
    },
    "shortcuts": [
        [
            "cataclysm-tiles.exe",
            "Cataclysm DDA\\Cataclysm DDA Tiles (Experimental)"
        ]
    ],
    "persist": [
        "config",
        "save",
        "sound",
        "templates"
    ],
    "checkver": {
        "url": "https://github.com/CleverRaven/Cataclysm-DDA/releases/",
        "re": "Cataclysm-DDA experimental build ([\\d.-]+)"
    },
    "autoupdate": {
        "architecture": {
            "64bit": {
                "url": "https://github.com/CleverRaven/Cataclysm-DDA/releases/download/cdda-experimental-$version/cdda-windows-tiles-sounds-x64-msvc-$version.zip"
            }
        }
    }
}
